hanzi_char_featurizer/__init__.py
hanzi_char_featurizer-0.1.dist-info/METADATA
hanzi_char_featurizer-0.1.dist-info/WHEEL
hanzi_char_featurizer-0.1.dist-info/top_level.txt
hanzi_char_featurizer-0.1.dist-info/RECORD
