Metadata-Version: 2.1
Name: hanzi-char-featurizer
Version: 0.1
Summary: UNKNOWN
Home-page: UNKNOWN
Author: Xiaoquan Kong
Author-email: u1mail2me@gmail.com
License: UNKNOWN
Platform: UNKNOWN
Requires-Dist: tensorflow (<2.0.0,>=1.15.0)
Requires-Dist: four-corner-method
Requires-Dist: pypinyin
